raksha69/__init__.py
raksha69/docs.py
raksha69/graph.py
raksha69/io.py
raksha69/tree.py
raksha69-1.0.0.dist-info/METADATA
raksha69-1.0.0.dist-info/WHEEL
raksha69-1.0.0.dist-info/top_level.txt
raksha69-1.0.0.dist-info/RECORD
